pagemarks/commands/__init__.py
pagemarks/commands/add.py
pagemarks/commands/build.py
pagemarks/commands/importer.py
pagemarks/commands/init.py
pagemarks/commands/locate.py
pagemarks/framework/__init__.py
pagemarks/framework/basecmd.py
pagemarks/framework/cmdline.py
pagemarks/framework/globals.py
pagemarks/framework/main.py
pagemarks/framework/render.py
pagemarks/framework/repo.py
pagemarks/framework/util.py
pagemarks/js/__init__.py
pagemarks/js/base32.js
pagemarks/js/css-theme.js
pagemarks/js/delete.js
pagemarks/js/edit.js
pagemarks/js/gitlab.js
pagemarks/js/globals.js
pagemarks/js/metadata.js
pagemarks/js/pagemarks.js
pagemarks/js/settings.js
pagemarks/js/spi.js
pagemarks/js/vendor/.gitkeep
pagemarks/js/vendor/core.js
pagemarks/js/vendor/sha1.js
pagemarks/js/vendor/tagify.min.js
pagemarks/js/vendor/tagify.polyfills.min.js
pagemarks/resources/__init__.py
pagemarks/resources/css/.gitkeep
pagemarks/resources/css/pagemarks_cerulean.css
pagemarks/resources/css/pagemarks_darkly.css
pagemarks/resources/css/pagemarks_minty.css
pagemarks/resources/css/pagemarks_sandstone.css
pagemarks/resources/css/pagemarks_superhero.css
pagemarks/resources/html/analytics_google.html
pagemarks/resources/html/analytics_plausible.html
pagemarks/resources/html/bookmark.html
pagemarks/resources/html/css-themes.json
pagemarks/resources/html/edit-bookmark.html
pagemarks/resources/html/index.html
pagemarks/resources/html/settings-apitoken.html
pagemarks/resources/repo/README.md
pagemarks/resources/repo/collection-template.json
pagemarks/resources/repo/gitlab-ci.yml
pagemarks/resources/sass/_modal.scss
pagemarks/resources/sass/_overrides.scss
pagemarks/resources/sass/_pagemarks.scss
pagemarks/resources/sass/_tag-editing.scss
pagemarks/resources/sass/main.scss
pagemarks-0.7.0.dist-info/LICENSE
pagemarks-0.7.0.dist-info/METADATA
pagemarks-0.7.0.dist-info/WHEEL
pagemarks-0.7.0.dist-info/entry_points.txt
pagemarks-0.7.0.dist-info/top_level.txt
pagemarks-0.7.0.dist-info/zip-safe
pagemarks-0.7.0.dist-info/RECORD
